{
  "count": 2,
  "repositories": [
    {
      "description": "The CLI tool to query AWS CloudWatch Logs Insights :mag:",
      "is_archive": false,
      "is_template": false,
      "language": "Python",
      "language_icon": "![python](https://homoluctus/ghc/icons/python.png)",
      "name": "pyinsights",
      "url": "https://github.com/homoluctus/pyinsights"
    },
    {
      "description": "Scan the vulnerability of Docker images stored in ECR",
      "is_archive": false,
      "is_template": false,
      "language": "Python",
      "language_icon": "![python](https://homoluctus/ghc/icons/python.png)",
      "name": "ecranner",
      "url": "https://github.com/homoluctus/ecranner"
    }
  ]
}